netdata_ts_clustering/__init__.py
netdata_ts_clustering/_nbdev.py
netdata_ts_clustering/core.py
netdata_ts_clustering-0.0.9.dist-info/LICENSE
netdata_ts_clustering-0.0.9.dist-info/METADATA
netdata_ts_clustering-0.0.9.dist-info/WHEEL
netdata_ts_clustering-0.0.9.dist-info/entry_points.txt
netdata_ts_clustering-0.0.9.dist-info/top_level.txt
netdata_ts_clustering-0.0.9.dist-info/RECORD
