Metadata-Version: 2.1
Name: netdata-ts-clustering
Version: 0.0.9
Summary: Time series clustering for netdata.
Home-page: https://github.com/andrewm4894/netdata_ts_clustering/tree/master/
Author: Andrew Maguire
Author-email: andrewmaguire@netdata.cloud
License: Apache Software License 2.0
Keywords: netdata clustering
Platform: UNKNOWN
Classifier: Development Status :: 3 - Alpha
Classifier: Intended Audience :: Developers
Classifier: License :: OSI Approved :: Apache Software License
Classifier: Natural Language :: English
Classifier: Programming Language :: Python :: 3.6
Classifier: Programming Language :: Python :: 3.7
Classifier: Programming Language :: Python :: 3.8
Requires-Python: >=3.6
Requires-Dist: am4894plots (==0.2.0)
Requires-Dist: netdata-pandas (==0.0.32)
Requires-Dist: plotly (==4.14.1)
Requires-Dist: tslearn (==0.4.1)
